{
  "_fv": 18,
  "_type": "recipe",
  "definition": {
    "recipeType": "Crafting",
    "xpReward": 0.0,
    "cookingTime": 200,
    "recipeRetstackSize": 1,
    "group": "nwtg_automation_remote_item_teleporter",
    "recipeShapeless": false,
    "recipeSlots": [
      {
        "value": ""
      },
      {
        "value": "Blocks.REDSTONE_TORCH"
      },
      {
        "value": ""
      },
      {
        "value": ""
      },
      {
        "value": "CUSTOM:MachineBlock"
      },
      {
        "value": ""
      },
      {
        "value": ""
      },
      {
        "value": "Blocks.HOPPER"
      },
      {
        "value": ""
      }
    ],
    "recipeReturnStack": {
      "value": "CUSTOM:RemoteItemTeleporter"
    },
    "name": "remote_item_teleporter",
    "namespace": "mod"
  }
}